acomms/__init__.py
acomms/_version.py
acomms/acomms_xmodem.py
acomms/ccl.py
acomms/commstate.py
acomms/cyclestats.py
acomms/flexibledataprotocol.py
acomms/index_list.py
acomms/messageparams.py
acomms/messageparser.py
acomms/micromodem.py
acomms/modemlog.py
acomms/net_modem.py
acomms/net_packet.py
acomms/nmealistener.py
acomms/pid_defs.py
acomms/ping.py
acomms/timeutil.py
acomms/unifiedlog.py
acomms/modem_connections/__init__.py
acomms/modem_connections/connection_utilities.py
acomms/modem_connections/iridium_connection.py
acomms/modem_connections/modem_connection.py
acomms/modem_connections/sbd_connection.py
acomms/modem_connections/serial_connection.py
acomms/modem_connections/tcp_client_connection.py
acomms/modem_connections/tcp_connection.py
acomms/modem_connections/udp_connection.py
acomms-3.1.0.dist-info/LICENSE.txt
acomms-3.1.0.dist-info/METADATA
acomms-3.1.0.dist-info/WHEEL
acomms-3.1.0.dist-info/top_level.txt
acomms-3.1.0.dist-info/RECORD
